qbeast_sharing/__init__.py
qbeast_sharing/_yarl_patch.py
qbeast_sharing/converter.py
qbeast_sharing/delta_sharing.py
qbeast_sharing/protocol.py
qbeast_sharing/reader.py
qbeast_sharing/rest_client.py
qbeast_sharing/version.py
qbeast_sharing-0.4.0.dev0.dist-info/METADATA
qbeast_sharing-0.4.0.dev0.dist-info/WHEEL
qbeast_sharing-0.4.0.dev0.dist-info/top_level.txt
qbeast_sharing-0.4.0.dev0.dist-info/RECORD
