Metadata-Version: 2.1
Name: qbeast-sharing
Version: 0.4.0.dev0
Summary: Python Connector for Delta Sharing
Home-page: https://github.com/Qbeast-io/qbeast-sharing
Author: The Delta Lake Project Authors and Qbeast Team
Author-email: users@qbeast.io
License: Apache-2.0
Project-URL: Source, https://github.com/Qbeast-io/qbeast-sharing
Project-URL: Documentation, https://github.com/Qbeast-io/qbeast-sharing
Project-URL: Issues, https://github.com/Qbeast-io/qbeast-sharing/issues
Classifier: Development Status :: 5 - Production/Stable
Classifier: Intended Audience :: Developers
Classifier: License :: OSI Approved :: Apache Software License
Classifier: Operating System :: OS Independent
Classifier: Topic :: Software Development :: Libraries :: Python Modules
Classifier: Programming Language :: Python :: 3.7
Classifier: Programming Language :: Python :: 3.8
Classifier: Programming Language :: Python :: 3.9
Requires-Python: >=3.7
Requires-Dist: pandas
Requires-Dist: pyarrow (>=4.0.0)
Requires-Dist: fsspec (>=0.7.4)
Requires-Dist: requests
Requires-Dist: aiohttp
Requires-Dist: yarl (>=1.6.0)
Requires-Dist: dataclasses ; python_version < "3.7"
Provides-Extra: abfs
Requires-Dist: adlfs ; extra == 'abfs'
Provides-Extra: adl
Requires-Dist: adlfs ; extra == 'adl'
Provides-Extra: gcs
Requires-Dist: gcsfs ; extra == 'gcs'
Provides-Extra: gs
Requires-Dist: gcsfs ; extra == 'gs'
Provides-Extra: s3
Requires-Dist: s3fs ; extra == 's3'
